xlogit/__init__.py
xlogit/_choice_model.py
xlogit/_device.py
xlogit/_optimize.py
xlogit/mixed_logit.py
xlogit/multinomial_logit.py
xlogit/utils.py
xlogit-0.2.7.dist-info/LICENSE
xlogit-0.2.7.dist-info/METADATA
xlogit-0.2.7.dist-info/WHEEL
xlogit-0.2.7.dist-info/top_level.txt
xlogit-0.2.7.dist-info/RECORD
