Metadata-Version: 2.1
Name: xlogit
Version: 0.2.7
Summary: A Python package for GPU-accelerated estimation of mixed logit models.
Home-page: https://github.com/arteagac/xlogit
Author: Cristian Arteaga
Author-email: cristiandavidarteaga@gmail.com
License: MIT
Requires-Python: >=3.5
License-File: LICENSE
Requires-Dist: numpy (>=1.13.1)
Requires-Dist: scipy (>=1.0.0)
